Metadata-Version: 2.1
Name: chatgpthon
Version: 0.1.0
Summary: A package to facilitate integration with chatgpt
Home-page: https://github.com/how-dev/chatgpython
Author: Howard Medeiros (howard.medeiros@gmail.com)
License: UNKNOWN
Keywords: chatgpthon
Platform: UNKNOWN
Classifier: Development Status :: 2 - Pre-Alpha
Classifier: Intended Audience :: Developers
Classifier: Natural Language :: English
Classifier: Programming Language :: Python :: 3.7
Classifier: Programming Language :: Python :: 3.8
Requires-Python: >=3.7
